AUTHORS.rst
CONTRIBUTING.rst
HISTORY.rst
LICENSE
MANIFEST.in
README.rst
setup.cfg
setup.py
docs/Makefile
docs/authors.rst
docs/conf.py
docs/contributing.rst
docs/history.rst
docs/index.rst
docs/installation.rst
docs/make.bat
docs/readme.rst
docs/usage.rst
docs/_build/html/_static/ajax-loader.gif
docs/_build/html/_static/comment-bright.png
docs/_build/html/_static/comment-close.png
docs/_build/html/_static/comment.png
docs/_build/html/_static/down-pressed.png
docs/_build/html/_static/down.png
docs/_build/html/_static/file.png
docs/_build/html/_static/minus.png
docs/_build/html/_static/plus.png
docs/_build/html/_static/up-pressed.png
docs/_build/html/_static/up.png
iol_api/__init__.py
iol_api/client.py
iol_api/constants.py
iol_api/ordenes.py
iol_api/token_manager.py
iol_api/utils.py
iol_api.egg-info/PKG-INFO
iol_api.egg-info/SOURCES.txt
iol_api.egg-info/dependency_links.txt
iol_api.egg-info/not-zip-safe
iol_api.egg-info/requires.txt
iol_api.egg-info/top_level.txt
tests/__init__.py
tests/test_iol_api.py