Metadata-Version: 1.2
Name: iol-api
Version: 0.1.1
Summary: IOL API wrapper
Home-page: https://github.com/cucasf/iol-api
Author: Lucas Matias Dentesani
Author-email: cucasf@outlook.com
License: MIT license
Keywords: iol_api,api,async,iol,invertir online
Platform: UNKNOWN
Classifier: Development Status :: 2 - Pre-Alpha
Classifier: Intended Audience :: Developers
Classifier: License :: OSI Approved :: MIT License
Classifier: Natural Language :: English
Classifier: Programming Language :: Python :: 3
Classifier: Programming Language :: Python :: 3.6
Classifier: Programming Language :: Python :: 3.7
Classifier: Programming Language :: Python :: 3.8
Requires-Python: >=3.6
